<?xml version="1.0" encoding="UTF-8"?>
<persistence xmlns="http://java.sun.com/xml/ns/persistence" version="2.0">

    <persistence-unit name="viewer">

        <class>at.spengergasse.trauner.entities.Patient</class>
        <class>at.spengergasse.trauner.entities.Study</class>
        <class>at.spengergasse.trauner.entities.Series</class>
        <class>at.spengergasse.trauner.entities.Instance</class>

        <properties>
            <property name="javax.persistence.jdbc.driver" value="com.mysql.jdbc.Driver" />
            <property name="javax.persistence.jdbc.url" value="jdbc:mysql://localhost/dicomDB" />
            <property name="javax.persistence.jdbc.user" value="root" />
            <property name="javax.persistence.jdbc.password" value="" />
            <property name="javax.persistence.schema-generation.database.action" value="create-or-extend-tables" />
        </properties>
    </persistence-unit>

</persistence>
